buildingsysid/__init__.py
buildingsysid/calculate/__init__.py
buildingsysid/calculate/optimization_manager.py
buildingsysid/calculate/pem_DEPRECATED.py
buildingsysid/calculate/solvers_DEPRECATED.py
buildingsysid/calculate/solvers/__init__.py
buildingsysid/calculate/solvers/least_squares_solver.py
buildingsysid/calculate/solvers/pso.py
buildingsysid/criterion_of_fit/__init__.py
buildingsysid/criterion_of_fit/objective_functions.py
buildingsysid/data/__init__.py
buildingsysid/data/iddata.py
buildingsysid/data/iddata_base.py
buildingsysid/data/iddata_correlation.py
buildingsysid/data/iddata_normalize.py
buildingsysid/data/iddata_resample.py
buildingsysid/data/iddata_split.py
buildingsysid/data/iddata_timeseriesplot.py
buildingsysid/model_set/__init__.py
buildingsysid/model_set/black/__init__.py
buildingsysid/model_set/black/base_blackbox.py
buildingsysid/model_set/black/canonical.py
buildingsysid/model_set/grey/__init__.py
buildingsysid/model_set/grey/base_greybox.py
buildingsysid/model_set/grey/base_greybox_DEPRECATED.py
buildingsysid/model_set/grey/predefined.py
buildingsysid/model_set/grey/DEPRECATED/first_order.py
buildingsysid/model_set/grey/DEPRECATED/fourth_order.py
buildingsysid/model_set/grey/DEPRECATED/second_order.py
buildingsysid/model_set/grey/DEPRECATED/third_order.py
buildingsysid/model_set/grey/DEPRECATED/third_test.py
buildingsysid/utils/__init__.py
buildingsysid/utils/blackbox_physical_properties.py
buildingsysid/utils/hankel.py
buildingsysid/utils/simulate_statespace.py
buildingsysid/utils/statespace.py
buildingsysid/utils/step_response.py
buildingsysid/validation/__init__.py
buildingsysid/validation/compare.py
buildingsysid/validation/residual_analysis.py
buildingsysid/validation/residual_analysis_functions.py
buildingsysid-0.1.4.dist-info/licenses/LICENSE.txt
buildingsysid-0.1.4.dist-info/METADATA
buildingsysid-0.1.4.dist-info/WHEEL
buildingsysid-0.1.4.dist-info/top_level.txt
buildingsysid-0.1.4.dist-info/RECORD
